code/config/__init__.py
code/config/parameter.py
code/dataloader/__init__.py
code/dataloader/data_dataloader.py
code/dataloader/path_dataloader.py
code/dataprocess/Food_Category.py
code/dataprocess/__init__.py
code/dataprocess/digital-recognizer.py
code/models/__init__.py
code/models/custom_model.py
code/utils/__init__.py
code/utils/loss_show.py
code/utils/util.py
mai/__init__.py
mai/version.py
mai/losses/__init__.py
mai/losses/contrastive.py
mai/losses/focalloss.py
mai/models/__init__.py
mai/models/densenet.py
mai/models/resnet.py
mai/models/resnetxt_wsl.py
mai/models/resnext.py
mai/models/resnext101_32x4d_features.py
mai/models/resnext101_64x4d_features.py
mai/models/senet.py
mai/models/detection/__init__.py
mai/models/detection/retinanet.py
mai/models/detection/retinanet_utils.py
mai/models/layers/__init__.py
mai/models/layers/anchors.py
mai/models/segmentation/__init__.py
mai/models/twin/__init__.py
mai/models/twin/simnet.py
mai/utils/__init__.py
mai/utils/util.py
mai-0.0.3.dist-info/LICENSE
mai-0.0.3.dist-info/METADATA
mai-0.0.3.dist-info/WHEEL
mai-0.0.3.dist-info/top_level.txt
mai-0.0.3.dist-info/RECORD
