Metadata-Version: 2.1
Name: mai
Version: 0.0.3
Summary: UNKNOWN
Home-page: https://gitee.com/whghcyx/sai
Author: hcyx
Author-email: whghcyx@outlook.com
License: UNKNOWN
Platform: UNKNOWN
Requires-Dist: torchsummaryX
Requires-Dist: flyai
Requires-Dist: torch (>=1.0.0)
